gpt_assistant_lib/__init__.py
gpt_assistant_lib/_assistant.py
gpt_assistant_lib/_exceptions.py
gpt_assistant_lib/_history.py
gpt_assistant_lib/_openai_client.py
gpt_assistant_lib/py.typed
gpt_assistant_lib-0.3.1.dist-info/LICENSE
gpt_assistant_lib-0.3.1.dist-info/METADATA
gpt_assistant_lib-0.3.1.dist-info/WHEEL
gpt_assistant_lib-0.3.1.dist-info/RECORD
