Metadata-Version: 2.1
Name: gpt-assistant-lib
Version: 0.3.1
Summary: Python library for your AI assistant, powered by GPT.
Home-page: https://github.com/elisey/gpt_assistant_lib
License: MIT
Author: Elisei
Author-email: elisey.rav@gmail.com
Requires-Python: >=3.11,<4.0
Classifier: License :: OSI Approved :: MIT License
Classifier: Programming Language :: Python :: 3
Classifier: Programming Language :: Python :: 3.11
Requires-Dist: openai (>=0.28.0,<0.29.0)
Project-URL: Repository, https://github.com/elisey/gpt_assistant_lib
